response_handler_lib/__init__.py
response_handler_lib/config.py
response_handler_lib/either.py
response_handler_lib/error_codes.py
response_handler_lib/errors.py
response_handler_lib/http_interceptor.py
response_handler_lib/response.py
tests/__init__.py
tests/test_config.py
tests/test_either.py
tests/test_http_interceptor.py
tests/test_response.py
response_handler_lib-0.2.0.dist-info/LICENSE
response_handler_lib-0.2.0.dist-info/METADATA
response_handler_lib-0.2.0.dist-info/WHEEL
response_handler_lib-0.2.0.dist-info/top_level.txt
response_handler_lib-0.2.0.dist-info/RECORD
