Metadata-Version: 2.1
Name: response-handler-lib
Version: 0.2.0
Summary: A package for handling responses with potential errors and generic data, including predefined and custom error handling. This package is used as a complement to exceptions to have more control over business logic errors.
Home-page: https://github.com/angerlkurten/response_handler_lib
Author: Angel Kürten
Author-email: angel@angelkurten.com
License: MIT
Platform: UNKNOWN
Classifier: Programming Language :: Python :: 3
Classifier: License :: OSI Approved :: MIT License
Classifier: Operating System :: OS Independent
Requires-Python: >=3.8
License-File: LICENSE
Requires-Dist: requests>=2.31.0
Requires-Dist: pydantic>=2.0.0
